{
  "page_type": "vietnamese_letters",
  "letters": [],
  "text_before_first_header": "quanh nên thành ra vì nhỏ mất lớn, được không bù nổi mất. Trong rất nhiều chuyện, có phiền phức và mệt mỏi hay không hoàn toàn phụ thuộc vào cách chúng ta nhìn nhận và xử lí nó. Đừng lúc nào cũng coi tất cả là chuyện lớn, đừng để tâm tới mấy chuyện tầm phào, đừng quá coi trọng thể diện, đừng nhỏ nhen hẹp hòi. Không để tâm chính là một kiểu rộng lượng và cởi mở.",
  "chinese_text_before_first_header": "反而因小失大，得不偿失。很多事情，烦不烦、累不累，完全取决于我们怎么看待和处理它。别什么都当成大事，别在意那些无聊的事，别太看重面子，别斤斤计较。不在乎，就是一种豁达和开朗。",
  "pinyin_text_before_first_header": "fǎn'ér yīn xiǎo shī dà, dé bù cháng shī. Hěn duō shìqíng, fán bù fán, lèi bù lèi, wánquán qǔjué yú wǒmen zěnme kàndài hé chǔlǐ tā. Bié shénme dōu dàngchéng dà shì, bié zàiyì nàxiē wúliáo de shì, bié tài kànzhòng miànzi, bié jīnjīn jìjiào. Bù zàihu, jiùshì yī zhǒng huòdá hé kāilǎng."
}