{
  "page_type": "bilingual_letter",
  "letter_number": 266,
  "chinese_text": "有些压力你必须独自承担，说出来只会变成抱怨和牢骚。寻求安慰也解决不了问题，反而会给他人增添烦恼。当你独自一人克服所有苦难时，一定会感激当初咬牙坚持至今的自己。",
  "pinyin_text": "Yǒu xiē yālì nǐ bìxū dúzì chéngdān, shuō chūlái zhǐ huì biànchéng bàoyuàn hé láosāo. Xúnqiú ānwèi yě jiějué bùliǎo wèntí, fǎn'ér huì gěi tā rén zēngtiān fánnǎo. Dāng nǐ dúzì yīrén kèfú suǒyǒu kǔnàn shí, yīdìng huì gǎnjī dāngchū yǎoyá jiānchí zhìjīn de zìjǐ.",
  "vietnamese_text": "Có những áp lực bạn phải tự mình gánh vác, nói ra sẽ thành những lời phàn nàn, ca thán. Tìm kiếm sự an ủi cũng không giải quyết được vấn đề mà còn gây thêm phiền toái cho người khác. Khi bạn một mình tự vượt qua mọi khổ nạn, nhất định sẽ cảm kích chính mình lúc trước đã cắn răng kiên trì đến hôm nay.",
  "source": "api_translation"
}