{
  "page_type": "bilingual_letter",
  "letter_number": 88,
  "chinese_text": "即便你现在如何迷茫，历经多少艰难困苦，疲惫不堪，但请相信，人生中有些路你必须独自走完。所以，请不要放弃希望，抛弃自己，无论多么艰难，都要努力奋斗。",
  "pinyin_text": "Jíbiàn nǐ xiànzài rúhé mímáng, lìjīng duōshǎo jiānnán kùnkǔ, píbéi bùkān, dàn qǐng xiāngxìn, rénshēng zhōng yǒuxiē lù nǐ bìxū dúzì zǒuwán. Suǒyǐ, qǐng bùyào fàngqì xīwàng, pāoqì zìjǐ, wúlùn duōme jiānnán, dōu yào nǔlì fèndòu.",
  "vietnamese_text": "Cho dù bây giờ bạn mơ hồ thế nào, trải qua bao nhiêu gian khó mệt mỏi, nhưng hãy tin rằng, trong cuộc đời có những quãng đường bạn bắt buộc một mình phải đi hết. Cho nên, xin đừng từ bỏ hy vọng , vứt bỏ bản thân, dù khó khăn đến đâu cũng phải cố gắng.",
  "source": "api_translation"
}