{
  "page_type": "bilingual_letter",
  "letter_number": 308,
  "chinese_text": "真正强大之人，皆须历经无人相助、无人支持的岁月。所有事务，皆由你一人承担；所有情感，唯有你心自知。然，只要咬牙坚持，挺过难关，一切终将柳暗花明。",
  "pinyin_text": "Zhēnzhèng qiángdà zhī rén, jiē xū lìjīng wú rén xiāngzhù, wú rén zhīchí de suìyuè. Suǒyǒu shìwù, jiē yóu nǐ yī rén chéngdān; suǒyǒu qínggǎn, wéiyǒu nǐ xīn zì zhī. Rán, zhǐyào yǎyá jiānchí, tǐngguò nánguān, yīqiè zhōng jiāng liǔ'àn huāmíng.",
  "vietnamese_text": "Người thực sự mạnh mẽ đều phải trải qua những ngày tháng không ai giúp đỡ hay ủng hộ. Tất cả mọi việc chỉ một mình bạn gánh vác, mọi cảm xúc chỉ có bản thân biết. Nhưng chỉ cần cắn răng chống đỡ vượt qua, tất cả đều sẽ đổi khác.",
  "source": "api_translation"
}