{
  "page_type": "bilingual_letter",
  "letter_number": 432,
  "chinese_text": "爱情中最无奈之处，莫过于两人阅历之悬殊。当你如初涉爱河的雏鸟般纯真，以为情深似海，而对方却已历经风雨，不愿再坠爱河。",
  "pinyin_text": "Àiqíng zhōng zuì wúnài zhī chù, mò guòyú liǎng rén yuèlì zhī xuánshū. Dāng nǐ rú chū shè àihé de chúnniǎo bān chúnzhēn, yǐwéi qíngshēn sìhǎi, ér duìfāng què yǐ lìjīng fēngyǔ, bù yuàn zài zhuì àihé.",
  "vietnamese_text": "Trong tình yêu điều bất lực nhất chính là sự từng trải của hai người không tương xứng. Khi bạn như chú chim non đơn thuần mới biết yêu, nghĩ tình sâu như biển, thì đối phương đã trải qua vạn sự gió mưa không muốn yêu thêm lần nữa.",
  "source": "api_translation"
}