{
  "page_type": "bilingual_letter",
  "letter_number": 320,
  "chinese_text": "终有一日，你蓦然发觉，他竟是唯一一个用自己最美好的青春岁月，与你共度风雨之人。如此之人，望你珍之重之。",
  "pinyin_text": "Zhōng yǒuyī rì, nǐ mòrán fājué, tā jìng shì wéiyī yīgè yòng zìjǐ zuì měihǎo de qīngchūn suìyuè, yǔ nǐ gòngdù fēngyǔ zhī rén. Rúcǐ zhī rén, wàng nǐ zhēn zhī zhòng zhī.",
  "vietnamese_text": "Có một ngày, bạn đột nhiên phát hiện ra, anh ấy là người duy nhất dùng những năm tháng thanh xuân đẹp đẽ của mình để cùng bạn trải qua bao gian khổ. Một người như thế, mong bạn hãy trân trọng.",
  "source": "api_translation"
}