{
  "page_type": "bilingual_letter",
  "letter_number": 384,
  "chinese_text": "我做好了与他共度一生的准备，也做好了他随时会走的准备，这或许是最好的爱情观，深爱但不依赖。",
  "pinyin_text": "Wǒ zuò hǎo le yǔ tā gòngdù yīshēng de zhǔnbèi, yě zuò hǎo le tā suíshí huì zǒu de zhǔnbèi, zhè huòxǔ shì zuì hǎo de àiqíngguān, shēn'ài dàn bù yīlài.",
  "vietnamese_text": "Tôi lên kế hoạch sẵn sàng sống cùng anh ấy trọn đời, nhưng cũng chuẩn bị sẵn sàng cho việc anh ấy có thể ra đi bất cứ lúc nào, có lẽ đây là quan điểm tốt nhất của tình yêu, yêu sâu đậm nhưng không phụ thuộc.",
  "source": "api_translation"
}