{
  "page_type": "bilingual_letter",
  "letter_number": 538,
  "chinese_text": "须经历几番背叛，几度苦痛，方能洞察人心。无人能操控你的人生，只是有时我们需更多勇气，以坚定自己的选择。有些记忆无法抹去，正如有些人无法替代。",
  "pinyin_text": "Xū jīnglì jǐ fān bèipàn, jǐ dù kǔtòng, fāng néng dòngchá rénxīn. Wú rén néng cāokòng nǐ de rénshēng, zhǐshì yǒushí wǒmen xū gèng duō yǒngqì, yǐ jiāndìng zìjǐ de xuǎnzé. Yǒuxiē jìyì wúfǎ mǒqù, zhèngrú yǒuxiē rén wúfǎ tìdài.",
  "vietnamese_text": "P hải trải qua đôi lần phản bội, vài lần đau khổ mới nhìn thấu được lòng người. Không ai có thể thao túng cuộc đời bạn, chỉ là đôi lúc chúng ta cần thêm chút dũng khí để kiên định với sự lựa chọn của chính mình. Có những ký ức không thể xóa bỏ, giống như có một số người không thể thay thế.",
  "source": "api_translation"
}