{
  "page_type": "bilingual_letter",
  "letter_number": 493,
  "chinese_text": "任何人的离开，都不是突然的决定。人心渐冷，叶子渐黄，故事渐写到结局。而爱情，是因失望积攒太多，才渐渐凋零。",
  "pinyin_text": "Rènhé rén de líkāi, dōu bùshì tūrán de juédìng. Rénxīn jiàn lěng, yèzi jiàn huáng, gùshì jiàn xiě dào jiéjú. Ér àiqíng, shì yīn shīwàng jīzǎn tài duō, cái jiànjiàn diāolíng.",
  "vietnamese_text": "Bất kỳ người nào rời xa bạn đều không phải quyết định đột nhiên. Lòng người dần trở nên lạnh nhạt, lá cây từ từ vàng úa, câu chuyện chậm chạp viết tới hồi kết. Còn tình yêu, là vì thất vọng chất chứa quá nhiều nên mới dần tàn lụi.",
  "source": "api_translation"
}